{
  "version": "",
  "pages": [
    {
      "url": "",
      "pageIdx": 0,
      "pageWidth": 1654,
      "pageHeight": 2339,
      "md": "<!-- Meanless: 视频日期：2024 年 5 月 5 日 -->\n\n题目:\n\n已知函数 \\( f\\left( x\\right)  = a{x}^{3} + b{x}^{2} + {cx} + d \\) 存在两个极值点 \\( {x}_{1},{x}_{2}\\left( {{x}_{1} < {x}_{2}}\\right) \\) ，且有 \\( f\\left( {x}_{1}\\right)  =  - {x}_{1} \\) ， \\( f\\left( {x}_{2}\\right)  = {x}_{2} \\) 。设 \\( f\\left( x\\right) \\) 的零点个数为 \\( m \\) ,方程 \\( {3a}{\\left( f\\left( x\\right) \\right) }^{2} + {2bf}\\left( x\\right)  + c = 0 \\) 的实根个数为 \\( n \\) , 则 \\( m + n \\) 的取值集合为___。\n\n这道题目条件较为繁杂。按照惯例, 我们先简单分析一下自由度, 看一下问题的结构。 \\( f\\left( x\\right) \\) 里有四个参数，也就是四个自由度。然后已知的两个等式减去两个自由度，因此系统总自由度是 2 。同时,系统的已知条件全部都围绕着两个极值点 \\( {x}_{1},{x}_{2} \\) 做文章,既有不等关系,给的牵制也全是关于它俩的。这自然就提示我们选 \\( {\\mathrm{x}}_{1},{\\mathrm{x}}_{2} \\) 作为主自由度,作为操纵杆控制整个系统。从刚才的自由度分析来看,只要知道了 \\( {\\mathrm{x}}_{1},{\\mathrm{x}}_{2} \\) ,就能定下 \\( \\mathrm{f}\\left( \\mathrm{x}\\right) \\) 。而且, 既然有两个极值点,那 \\( \\mathrm{f}\\left( \\mathrm{x}\\right) \\) 必定是三次函数了, \\( \\mathrm{a} \\neq  0 \\) 。\n\n怎么定呢? 这个元问题是要去刻画 \\( \\mathrm{f}\\left( \\mathrm{x}\\right) \\) 的形态,显然直接关系到问题的解决,因此可以先做一个思考。运用画图的方法, 把极值点尝试标在坐标系里, 我们立刻就会发现, 极值点的位置分布对 \\( \\mathrm{f}\\left( \\mathrm{x}\\right) \\) 的形态有巨大的影响。因此,我们不得不使用遍历法来进行分析, 以保证所有情况不遗漏。这是一个双自由度的遍历过程, 因此冻结法的使用也是必然的。我们可以先做点思想试验以大致找找感觉。遍历通常是以极端情况起手，比如主自由度很小或者很大。比如我们先假设 \\( {\\mathrm{x}}_{1} =  - {100} \\) ,这样可以再取 \\( {\\mathrm{x}}_{2} =  - {50} \\) 。在坐标系上画出两点 \\( \\left( {-{100},{100}}\\right) ,\\left( {-{50}, - {50}}\\right) \\) ,很容易看出 \\( \\mathrm{f}\\left( \\mathrm{x}\\right) \\) 是增减增的模式,且有三个零点。这样啊, 看来想分析清楚也不是很难啊。这种情况无非就是标标点, 画画图, 已经可以预见其他情况也无非就是这样了。于是, 我们对这个元问题的分析大致有了信心了。\n\n在真正起手遍历之前，我们还得把所求做一个充要替换，以方便我们遍历时直接观测。 第一个 \\( \\mathrm{m} \\) 是零点个数，可以直接读图像读出来。第二个有点诡异。这显然是两层方程：首先求解 \\( 3{\\mathrm{{at}}}^{2} + 2\\mathrm{{bt}} + \\mathrm{c} = 0 \\) ,解出全部 \\( \\mathrm{t} \\) ,然后再把所有 \\( \\mathrm{f}\\left( \\mathrm{x}\\right)  = \\mathrm{t} \\) 的解取并集 (注意是取并集, 这考察大家基本的元问题掌握)。既然是两层, 我们自然需要先把思维焦点放到二次方程 \\( 3{\\mathrm{{at}}}^{2} + 2\\mathrm{{bt}} + \\mathrm{c} = 0 \\) 上。这是什么? 隔离出来观察,不难看出这就是 \\( {\\mathrm{f}}^{\\prime }\\left( \\mathrm{t}\\right)  = 0 \\) ,因此从题目描述来看,它正好对应 \\( {x}_{1},{x}_{2} \\) 这两个解,所以原方程就等价于 \\( f\\left( x\\right)  = {x}_{1},{x}_{2} \\) 这两个方程解的并集。",
      "score": 0
    },
    {
      "url": "",
      "pageIdx": 1,
      "pageWidth": 1654,
      "pageHeight": 2339,
      "md": "\n\n基本的充要替换做完了, 现在我们可以开始冻结与遍历了。首先, 冻结谁呢? 两个极值点地位也没啥区别,所以先冻结谁都行。我们就先冻结 \\( {\\mathrm{x}}_{1} \\) 吧。然后遍历 \\( {\\mathrm{x}}_{2} \\in  \\left( {{\\mathrm{x}}_{1}, + \\infty }\\right) \\) 。 那冻结的 \\( {\\mathrm{x}}_{1} \\) 的位置也对题目有影响,所以也得先对 \\( {\\mathrm{x}}_{1} \\) 做点讨论。\n\n首先,如果 \\( {\\mathrm{x}}_{1} \\) 非常小,比如是 -10000,-1000 这样的。点一下 \\( {\\mathrm{x}}_{1} \\) ,然后遍历 \\( {\\mathrm{x}}_{2} \\circ  {\\mathrm{x}}_{2} \\) 起手自然是 \\( {\\mathrm{x}}_{1} \\) 附近,这时不难发现,和之前我们的例子是类似的, \\( \\mathrm{f}\\left( \\mathrm{x}\\right) \\) 的零点数 \\( \\mathrm{m} = 3 \\) 。 看 \\( \\mathrm{n} \\) 的话需要再画出 \\( \\mathrm{y} = {\\mathrm{x}}_{1},\\mathrm{y} = {\\mathrm{x}}_{2} \\) 两条横截线。显然它们与 \\( \\mathrm{f}\\left( \\mathrm{x}\\right) \\) 交点数目分别为1,2,且零点彼此不重复,于是 \\( \\mathrm{n} = 3 \\) ,此时 \\( \\mathrm{m} + \\mathrm{n} = 6 \\) ,得到一个答案。\n\n继续遍历,增大 \\( {\\mathrm{x}}_{2} \\) ,不难发现只要 \\( {\\mathrm{x}}_{2} < 0 \\) ,刚才的讨论都仍然适用,此时 \\( \\mathrm{m} + \\mathrm{n} = 6 \\) 继续保持。当 \\( {\\mathrm{x}}_{2} = 0 \\) 时,问题出现了转机。这时 \\( \\mathrm{f}\\left( \\mathrm{x}\\right) \\) 只有两个零点了, \\( \\mathrm{m} = 2 \\) ,但是 \\( \\mathrm{n} \\) 仍然是 3,因此 \\( \\mathrm{m} + \\mathrm{n} = 5 \\) ,又一个答案。\n\n继续增大 \\( {\\mathrm{x}}_{2} \\) 。如果 \\( {\\mathrm{x}}_{2} \\) 只大了一点点,比如只是 0.01,这时 \\( \\mathrm{f}\\left( \\mathrm{x}\\right) \\) 还是增减增模式,此时 \\( \\mathrm{m} = 1 \\) ，但仍然 \\( \\mathrm{n} = 3 \\) ，因此第三个答案： \\( \\mathrm{m} + \\mathrm{n} = 4 \\) 。并且显然：如果 \\( {\\mathrm{x}}_{2} \\) 仍然不大的话， 这个模式会继续保持\n\n继续增大 \\( {\\mathrm{X}}_{2} \\) 。如果 \\( {\\mathrm{X}}_{2} =  - {\\mathrm{X}}_{1} \\) ,这时两个极值平齐,这对三次函数显然不可能,淘汰掉。 再增大 \\( {\\mathrm{X}}_{2} \\) 的话, \\( \\mathrm{f}\\left( \\mathrm{x}\\right) \\) 就要翻转成减增减模式了。此时不难看出,仍然是 \\( \\mathrm{m} = 1,\\mathrm{n} = 3 \\) ,因此没有新增的答案。继续让 \\( {\\mathrm{x}}_{2} \\) 跑到正无穷,也仍然是这种模式。\n\n这种 \\( {\\mathrm{X}}_{1} \\) 冻结情况下, \\( {\\mathrm{X}}_{2} \\) 的遍历完成了。因此我们可以考虑其他的 \\( {\\mathrm{X}}_{1} \\) 了。不难看出: 不管取 \\( {\\mathrm{x}}_{1} \\) 是 -10000,-100 还是 -1 。它的 \\( {\\mathrm{x}}_{2} \\) 遍历模式都一样。因此下一步我们直接上 \\( {\\mathrm{x}}_{1} = 0 \\) 。 这时必须 \\( {\\mathrm{x}}_{2} > 0 \\) 。遍历 \\( {\\mathrm{x}}_{2} \\) ，显然此时 \\( \\mathrm{f}\\left( \\mathrm{x}\\right) \\) 只能是减增减模式， \\( \\mathrm{m} = 2 \\) 。再考虑两条横截线 \\( y = 0,y = {x}_{2} \\) ,不难看出它俩各自与 \\( f\\left( x\\right) \\) 有两个交点,且这四个零点彼此不重复,因此 \\( \\mathrm{n} = 4 \\) ,此时 \\( \\mathrm{m} + \\mathrm{n} = 6 \\) ,仍然是之前有过的答案。不管怎么遍历 \\( {\\mathrm{x}}_{2} > 0 \\) ,此模式都不变。",
      "score": 0
    },
    {
      "url": "",
      "pageIdx": 2,
      "pageWidth": 1654,
      "pageHeight": 2339,
      "md": "\n\n下一步只能继续增大 \\( {\\mathrm{X}}_{1} \\) ,然后让 \\( {\\mathrm{X}}_{2} > {\\mathrm{X}}_{1} \\) 。此时 \\( \\mathrm{f}\\left( \\mathrm{x}\\right) \\) 还是减增减,但是有三个零点了, \\( \\mathrm{m} = 3 \\) 。再画两条横截线 \\( \\mathrm{y} = {\\mathrm{x}}_{1},\\mathrm{y} = {\\mathrm{x}}_{2} \\) ,显然它们与 \\( \\mathrm{f}\\left( \\mathrm{x}\\right) \\) 分别横截于3,2个点,且彼此不重复,因此 \\( \\mathrm{n} = 5 \\) ,此时 \\( \\mathrm{m} + \\mathrm{n} = 8 \\) ,有了一个新答案。不难看出 \\( {\\mathrm{x}}_{2} > {\\mathrm{x}}_{1} > 0 \\) 全是这种模式。\n\n综合一下,最终答案就是 \\( \\{ 4,5,6,8\\} \\) 。顺便说一下这道题即时检查的方式。由于这道题在画横线的时候可能会出现错误, 而且除了画图之外没有什么其他解法, 也不方便大家重算, 因此建议带入特殊值来进行检查。具体来说, 就是上面的那些情况, 你可以每种情况取一个 \\( {x}_{1},{x}_{2} \\) 的特殊值进行静态问题分析,具体地把那两条横截线的数值写出来。另外, 这道题的检查可以往后拖一拖, 制造一定的时间差, 从而降低刚才解题时思维惯性的影响。\n\n这道题虽然可以排到高考真题压轴填空的难度, 但想做出来并不困难。考察的就是基本的思维方式: 冻结法和遍历法的运用。近期有不少同学在私信提问的时候都暴露出了遍历法意识不强的问题。遍历法是经验分享第二期里重点出现的, 十分重要的思维方式, 需要引起大家的重视。它是用来不重复不遗漏地刻画自由度的行为, 保持了系统的信息量, 在相当多的问题中都有广泛的应用。大家应当重视这样的思维, 通过使用这种思维来强化自己充要替换的意识，提升自己思维的严谨性。",
      "score": 0
    }
  ]
}